README.md
setup.py
monutils/__init__.py
monutils/cache.py
monutils/copy.py
monutils/db.py
monutils.egg-info/PKG-INFO
monutils.egg-info/SOURCES.txt
monutils.egg-info/dependency_links.txt
monutils.egg-info/entry_points.txt
monutils.egg-info/requires.txt
monutils.egg-info/top_level.txt
monutils/args/__init__.py
monutils/args/copy.py
monutils/args/mongo.py
test/test_connection.py