Metadata-Version: 2.1
Name: monutils
Version: 0.1.9
Summary: Small Python utils to deal with MongoDB.
Home-page: https://github.com/jmgomezsoriano/mongoutils
Author: José Manuel Gómez Soriano
Author-email: jmgomez.soriano@gmail.com
License: LGPL2
Classifier: Programming Language :: Python :: 3
Classifier: License :: OSI Approved :: MIT License
Classifier: Operating System :: OS Independent
Requires-Python: >=3.7,<4
Requires-Dist: mysmallutils<2.1,>=1.1.9
Requires-Dist: pymongo<4.0,>=3.0
